roomor/__init__.py
roomor/geometric_util.py
roomor/model_manager.py
roomor/room_generator_factory.py
roomor/version.py
roomor/generator/__init__.py
roomor/generator/chest_room.py
roomor/generator/cube_room.py
roomor-0.3.1.dist-info/LICENSE
roomor-0.3.1.dist-info/METADATA
roomor-0.3.1.dist-info/WHEEL
roomor-0.3.1.dist-info/top_level.txt
roomor-0.3.1.dist-info/RECORD
