Metadata-Version: 2.1
Name: roomor
Version: 0.3.1
Summary: A Python framework for generating and deploying random room for Gazebo
Home-page: https://github.com/wwwshwww/roomor
Author: Reona Sato
Author-email: www.shinderu.www@gmail.com
License: UNKNOWN
Keywords: gazebo ros simulation robotics randomized-environment reinforcement-learning-environments pcg_gazebo randoor
Platform: UNKNOWN
Classifier: License :: OSI Approved :: MIT License
Classifier: Programming Language :: Python :: 2.7
Classifier: Programming Language :: Python :: 3.6
Classifier: Programming Language :: Python :: 3.7
Classifier: Programming Language :: Python :: 3.8
Classifier: Programming Language :: Python :: 3.9
Classifier: Programming Language :: Python :: 3.10
License-File: LICENSE
Requires-Dist: randoor
Requires-Dist: pcg-gazebo (==0.7.12)
Requires-Dist: trimesh
